{"name":"test001","id":"com.gorest.curdtest.GoRestCURDTest:test001","testCaseName":"com.gorest.curdtest.GoRestCURDTest","testSteps":[{"number":1,"description":"Getting all users records","duration":2976,"startTime":"2023-01-03T18:02:37.867Z[Europe/London]","result":"SUCCESS","precondition":false,"children":[{"number":2,"description":"GET https://gorest.co.in/public/v2/users\r\r","duration":1,"startTime":"2023-01-03T18:02:40.806Z[Europe/London]","result":"SUCCESS","restQuery":{"method":"GET","path":"https://gorest.co.in/public/v2/users\r\r","content":"\r","contentType":"null","requestHeaders":"Authorization\u003dBearer a329e99dc701baa9a84abdaf264dd68759c23dc0a094a98348a2c9e5d7173d32\r\n\t\t\t\tConnection\u003dkeep-alive\r\n\t\t\t\tAccept\u003d*/*\r\r","requestCookies":"\r\r","responseHeaders":"Date: Tue, 03 Jan 2023 18:02:37 GMT\nContent-Type: application/json; charset\u003dutf-8\nTransfer-Encoding: chunked\nConnection: keep-alive\nCache-Control: max-age\u003d0, private, must-revalidate\netag: W/\"ae1d8192825ecb18ce622e7892fe91c8\"\nreferrer-policy: strict-origin-when-cross-origin\nvary: Origin\nx-content-type-options: nosniff\nx-download-options: noopen\nx-frame-options: SAMEORIGIN\nx-links-current: https://gorest.co.in/public/v2/users?page\u003d1\nx-links-next: https://gorest.co.in/public/v2/users?page\u003d2\nx-links-previous: \nx-pagination-limit: 10\nx-pagination-page: 1\nx-pagination-pages: 425\nx-pagination-total: 4250\nx-permitted-cross-domain-policies: none\nx-ratelimit-limit: 90\nx-ratelimit-remaining: 88\nx-ratelimit-reset: 1\nx-request-id: 9d6fffc1-898f-4238-a62e-6c3819c827f4\nx-runtime: 0.065527\nx-xss-protection: 0\nCF-Cache-Status: DYNAMIC\nReport-To: {\"endpoints\":[{\"url\":\"https:\\/\\/a.nel.cloudflare.com\\/report\\/v3?s\u003dFlftAHTbeFEJAKtALlmnDeS2tc8i52hAXikGKPnhU3hDI5zQWcMM7VioTStw7FojA8MF0wbbrke1KQ7HMgEdrcol%2FnCRRVKbwOlSFLvtufwkteTilnS5tM%2Bb8BItMKU%3D\"}],\"group\":\"cf-nel\",\"max_age\":604800}\nNEL: {\"success_fraction\":0,\"report_to\":\"cf-nel\",\"max_age\":604800}\nServer: cloudflare\nCF-RAY: 783da57afc5ae688-LHR\nContent-Encoding: gzip\nalt-svc: h3\u003d\":443\"; ma\u003d86400, h3-29\u003d\":443\"; ma\u003d86400\r","responseCookies":"\r","responseBody":"[\n    {\n        \"id\": 27171,\n        \"name\": \"nik\",\n        \"email\": \"nik152194@gmail.com\",\n        \"gender\": \"male\",\n        \"status\": \"inactive\"\n    },\n    {\n        \"id\": 27170,\n        \"name\": \"nik\",\n        \"email\": \"nik543825@gmail.com\",\n        \"gender\": \"male\",\n        \"status\": \"active\"\n    },\n    {\n        \"id\": 27169,\n        \"name\": \"nik\",\n        \"email\": \"nik602233@gmail.com\",\n        \"gender\": \"male\",\n        \"status\": \"inactive\"\n    },\n    {\n        \"id\": 27168,\n        \"name\": \"nik\",\n        \"email\": \"nik139936@gmail.com\",\n        \"gender\": \"male\",\n        \"status\": \"inactive\"\n    },\n    {\n        \"id\": 27166,\n        \"name\": \"nik\",\n        \"email\": \"nik62275@gmail.com\",\n        \"gender\": \"male\",\n        \"status\": \"inactive\"\n    },\n    {\n        \"id\": 27153,\n        \"name\": \"nik\",\n        \"email\": \"nik80@gmail.com\",\n        \"gender\": \"male\",\n        \"status\": \"inactive\"\n    },\n    {\n        \"id\": 27151,\n        \"name\": \"nik\",\n        \"email\": \"nik55@gmail.com\",\n        \"gender\": \"male\",\n        \"status\": \"inactive\"\n    },\n    {\n        \"id\": 27150,\n        \"name\": \"nik\",\n        \"email\": \"nik62@gmail.com\",\n        \"gender\": \"male\",\n        \"status\": \"inactive\"\n    },\n    {\n        \"id\": 27149,\n        \"name\": \"nik\",\n        \"email\": \"nik20@gmail.com\",\n        \"gender\": \"male\",\n        \"status\": \"inactive\"\n    },\n    {\n        \"id\": 27148,\n        \"name\": \"nik\",\n        \"email\": \"nik7@gmail.com\",\n        \"gender\": \"male\",\n        \"status\": \"inactive\"\n    }\n]","statusCode":200},"precondition":false}]}],"userStory":{"id":"com.gorest.curdtest.GoRestCURDTest","storyName":"Go rest CURD test","storyClassName":"com.gorest.curdtest.GoRestCURDTest","path":"com.gorest.curdtest","type":"story"},"featureTag":{"name":"Curdtest/Go rest CURD test","type":"story"},"title":"This method will get all users records","tags":[{"name":"Curdtest/Go rest CURD test","type":"story"}],"startTime":"2023-01-03T18:02:37.796Z[Europe/London]","duration":3053,"projectKey":"","manual":false,"testSource":"JUnit","result":"SUCCESS"}